{
    "tags": null,
    "position": [
        0,
        0,
        0
    ],
    "rotation": [
        0,
        0,
        0
    ],
    "rotationQuaternion": [
        0,
        0,
        0,
        1
    ],
    "scaling": [
        1,
        1,
        1
    ],
    "billboardMode": 0,
    "scalingDeterminant": 1,
    "infiniteDistance": false,
    "ignoreNonUniformScaling": false,
    "reIntegrateRotationIntoRotationQuaternion": false,
    "name": "Pine_4",
    "id": "699216d1-0876-43ca-88b1-cdc10506db0d",
    "state": "",
    "metadata": {
        "parentId": 1740501054954
    },
    "type": "TransformNode",
    "uniqueId": 1740501054957,
    "localMatrix": [
        1,
        0,
        0,
        0,
        0,
        1,
        0,
        0,
        0,
        0,
        1,
        0,
        0,
        0,
        0,
        1
    ],
    "isEnabled": true,
    "animations": [],
    "ranges": []
}
